pilot/__init__.py
pilot/conversation.py
pilot/logs.py
pilot/singleton.py
pilot/utils.py
pilot/agent/__init__.py
pilot/agent/agent.py
pilot/agent/agent_manager.py
pilot/agent/json_fix_llm.py
pilot/chain/__init__.py
pilot/chain/audio.py
pilot/chain/visual.py
pilot/commands/__init__.py
pilot/commands/command.py
pilot/commands/command_mange.py
pilot/commands/exception_not_commands.py
pilot/commands/times.py
pilot/commands/built_in/__init__.py
pilot/commands/built_in/audio_text.py
pilot/commands/built_in/image_gen.py
pilot/common/__init__.py
pilot/common/custom_data_structure.py
pilot/common/formatting.py
pilot/common/markdown_text.py
pilot/common/plugins.py
pilot/common/schema.py
pilot/common/sql_database.py
pilot/configs/__init__.py
pilot/configs/config.py
pilot/configs/model_config.py
pilot/embedding_engine/EncodeTextLoader.py
pilot/embedding_engine/__init__.py
pilot/embedding_engine/chn_document_splitter.py
pilot/embedding_engine/csv_embedding.py
pilot/embedding_engine/embedding_engine.py
pilot/embedding_engine/knowledge_embedding.py
pilot/embedding_engine/knowledge_type.py
pilot/embedding_engine/markdown_embedding.py
pilot/embedding_engine/pdf_embedding.py
pilot/embedding_engine/pdf_loader.py
pilot/embedding_engine/ppt_embedding.py
pilot/embedding_engine/search_milvus.py
pilot/embedding_engine/source_embedding.py
pilot/embedding_engine/string_embedding.py
pilot/embedding_engine/url_embedding.py
pilot/embedding_engine/word_embedding.py
pilot/embedding_engine/external/__init__.py
pilot/inference_parsers/__init__.py
pilot/inference_parsers/base.py
pilot/json_utils/__init__.py
pilot/json_utils/json_fix_general.py
pilot/json_utils/utilities.py
pilot/log/__init__.py
pilot/log/json_handler.py
pilot/memory/__init__.py
pilot/memory/chat_history/__init__.py
pilot/memory/chat_history/base.py
pilot/memory/chat_history/duckdb_history.py
pilot/memory/chat_history/file_history.py
pilot/memory/chat_history/mem_history.py
pilot/model/__init__.py
pilot/model/adapter.py
db_gpt-0.3.0.dist-info/LICENSE
db_gpt-0.3.0.dist-info/METADATA
db_gpt-0.3.0.dist-info/WHEEL
db_gpt-0.3.0.dist-info/entry_points.txt
db_gpt-0.3.0.dist-info/top_level.txt
db_gpt-0.3.0.dist-info/RECORD
