Metadata-Version: 2.1
Name: db-gpt
Version: 0.3.0
Summary: DB-GPT is an experimental open-source project that uses localized GPT large models to interact with your data and environment. With this solution, you can be assured that there is no risk of data leakage, and your data is 100% private and secure.
Home-page: https://github.com/csunny/DB-GPT
Author: csunny
Author-email: cfqcsunny@gmail.com
License: https://opensource.org/license/mit/
Requires-Python: >=3.10
License-File: LICENSE
Requires-Dist: torch (==2.0.0)
Requires-Dist: accelerate (==0.16.0)
Requires-Dist: aiohttp (==3.8.4)
Requires-Dist: aiosignal (==1.3.1)
Requires-Dist: async-timeout (==4.0.2)
Requires-Dist: attrs (==22.2.0)
Requires-Dist: bitsandbytes (==0.39.0)
Requires-Dist: cchardet (==2.1.7)
Requires-Dist: chardet (==5.1.0)
Requires-Dist: contourpy (==1.0.7)
Requires-Dist: cycler (==0.11.0)
Requires-Dist: filelock (==3.9.0)
Requires-Dist: fonttools (==4.38.0)
Requires-Dist: frozenlist (==1.3.3)
Requires-Dist: huggingface-hub (==0.14.1)
Requires-Dist: importlib-resources (==5.12.0)
Requires-Dist: sqlparse (==0.4.4)
Requires-Dist: kiwisolver (==1.4.4)
Requires-Dist: matplotlib (==3.7.1)
Requires-Dist: multidict (==6.0.4)
Requires-Dist: packaging (==23.0)
Requires-Dist: psutil (==5.9.4)
Requires-Dist: pycocotools (==2.0.6)
Requires-Dist: pyparsing (==3.0.9)
Requires-Dist: python-dateutil (==2.8.2)
Requires-Dist: pyyaml (==6.0)
Requires-Dist: tokenizers (==0.13.2)
Requires-Dist: tqdm (==4.64.1)
Requires-Dist: transformers (==4.30.0)
Requires-Dist: timm (==0.6.13)
Requires-Dist: spacy (==3.5.3)
Requires-Dist: webdataset (==0.2.48)
Requires-Dist: yarl (==1.8.2)
Requires-Dist: zipp (==3.14.0)
Requires-Dist: omegaconf (==2.3.0)
Requires-Dist: opencv-python (==4.7.0.72)
Requires-Dist: iopath (==0.1.10)
Requires-Dist: tenacity (==8.2.2)
Requires-Dist: peft
Requires-Dist: pycocoevalcap
Requires-Dist: cpm-kernels
Requires-Dist: umap-learn
Requires-Dist: notebook
Requires-Dist: gradio (==3.23)
Requires-Dist: gradio-client (==0.0.8)
Requires-Dist: wandb
Requires-Dist: llama-index (==0.5.27)
Requires-Dist: pymysql
Requires-Dist: unstructured (==0.6.3)
Requires-Dist: grpcio (==1.47.5)
Requires-Dist: gpt4all (==0.3.0)
Requires-Dist: diskcache (==5.6.1)
Requires-Dist: auto-gpt-plugin-template
Requires-Dist: pymdown-extensions
Requires-Dist: gTTS (==2.3.1)
Requires-Dist: langchain
Requires-Dist: nltk
Requires-Dist: python-dotenv (==1.0.0)
Requires-Dist: pymilvus (==2.2.1)
Requires-Dist: vcrpy
Requires-Dist: chromadb (==0.3.22)
Requires-Dist: markdown2
Requires-Dist: colorama
Requires-Dist: playsound
Requires-Dist: distro
Requires-Dist: pypdf
Requires-Dist: weaviate-client
Requires-Dist: pytest
Requires-Dist: asynctest
Requires-Dist: pytest-asyncio
Requires-Dist: pytest-benchmark
Requires-Dist: pytest-cov
Requires-Dist: pytest-integration
Requires-Dist: pytest-mock
Requires-Dist: pytest-recording
Requires-Dist: pytesseract (==0.3.10)
